setup.py
distributionsabcd/Binomialdistribution.py
distributionsabcd/Gaussiandistribution.py
distributionsabcd/Generaldistribution.py
distributionsabcd/__init__.py
distributionsabcd.egg-info/PKG-INFO
distributionsabcd.egg-info/SOURCES.txt
distributionsabcd.egg-info/dependency_links.txt
distributionsabcd.egg-info/not-zip-safe
distributionsabcd.egg-info/top_level.txt